datatour/__init__.py
datatour/datatour.py
datatour/py.typed
datatour/dtutils/__init__.py
datatour/dtutils/examples.py
datatour/dtutils/log.py
datatour/dtutils/preproc.py
datatour/dtutils/rotations.py
datatour-0.2.9.dist-info/METADATA
datatour-0.2.9.dist-info/WHEEL
datatour-0.2.9.dist-info/licenses/LICENSE
datatour-0.2.9.dist-info/RECORD
