Metadata-Version: 2.4
Name: datatour
Version: 0.2.9
Summary: Seeing is important. `datatour` - allows you to see your data in it's native dimension. Currently implemented as a `plotly` scatter plot projected from it's original dimension in the 2D on the screen with timeline animation inspired by GrandTour and common sense. 
Project-URL: homepage, https://github.com/neworldemancer/datatour_pkg
Project-URL: repository, https://github.com/neworldemancer/datatour_pkg
Author-email: Mykhailo Vladymyrov <neworldemancer@gmail.com>
License: BSD-3-Clause
License-File: LICENSE
Classifier: Development Status :: 3 - Alpha
Classifier: License :: OSI Approved :: BSD License
Classifier: Programming Language :: Python :: 3
Classifier: Programming Language :: Python :: 3.8
Classifier: Programming Language :: Python :: 3.9
Classifier: Programming Language :: Python :: 3.10
Classifier: Programming Language :: Python :: 3.11
Classifier: Programming Language :: Python :: 3.12
Classifier: Typing :: Typed
Requires-Python: >=3.8
Requires-Dist: numpy
Requires-Dist: pandas
Requires-Dist: plotly
Requires-Dist: scipy
Provides-Extra: dev
Requires-Dist: ipython; extra == 'dev'
Requires-Dist: mypy; extra == 'dev'
Requires-Dist: pdbpp; extra == 'dev'
Requires-Dist: pre-commit; extra == 'dev'
Requires-Dist: rich; extra == 'dev'
Requires-Dist: ruff; extra == 'dev'
Provides-Extra: test
Requires-Dist: pytest; extra == 'test'
Requires-Dist: pytest-cov; extra == 'test'
